makepackage/__init__.py
makepackage/__main__.py
makepackage/makepackage.py
makepackage/write_CLI_main.py
makepackage/write_README.py
makepackage/write_conftest.py
makepackage/write_gitignore.py
makepackage/write_license.py
makepackage/write_module.py
makepackage/write_module_init.py
makepackage/write_pyproject.py
makepackage/write_pytest_ini.py
makepackage/write_setup.py
makepackage/write_tests.py
makepackage/write_tests_init.py
makepackage-0.2.2.dist-info/licenses/LICENSE
makepackage-0.2.2.dist-info/METADATA
makepackage-0.2.2.dist-info/WHEEL
makepackage-0.2.2.dist-info/entry_points.txt
makepackage-0.2.2.dist-info/top_level.txt
makepackage-0.2.2.dist-info/RECORD
