Metadata-Version: 2.4
Name: makepackage
Version: 0.2.2
Summary: Creating a structure of a simple Python package
Author-email: Nyggus <nyggus@gmail.com>, Patrick Boateng <boatengpato.pb@gmail.com>
License: MIT License
Project-URL: Homepage, https://github.com/nyggus/makepackage/
Classifier: Programming Language :: Python :: 3
Classifier: License :: OSI Approved :: MIT License
Classifier: Operating System :: OS Independent
Requires-Python: >=3.6
License-File: LICENSE
Requires-Dist: easycheck
Provides-Extra: dev
Requires-Dist: wheel; extra == "dev"
Requires-Dist: black; extra == "dev"
Requires-Dist: pytest; extra == "dev"
Requires-Dist: mypy; extra == "dev"
Requires-Dist: setuptools; extra == "dev"
Requires-Dist: build; extra == "dev"
Dynamic: license-file
